README.md
pyproject.toml
setup.py
FastaFragmentor.egg-info/PKG-INFO
FastaFragmentor.egg-info/SOURCES.txt
FastaFragmentor.egg-info/dependency_links.txt
FastaFragmentor.egg-info/requires.txt
FastaFragmentor.egg-info/top_level.txt
fasta_digest/__init__.py
fasta_digest/digest.py