Metadata-Version: 1.0
Name: FastaFragmentor
Version: 0.0.4
Summary: Split fasta sequences into fragments of given length.
Home-page: UNKNOWN
Author: UNKNOWN
Author-email: UNKNOWN
License: MIT
Platform: UNKNOWN
